{
	"cmake" : 
	{
		"generator" : 
		{
			"multiConfig" : false,
			"name" : "Ninja"
		},
		"paths" : 
		{
			"cmake" : "/nix/store/np45wjc61sy6d021dnrgyizga8f859k5-cmake-3.31.6/bin/cmake",
			"cpack" : "/nix/store/np45wjc61sy6d021dnrgyizga8f859k5-cmake-3.31.6/bin/cpack",
			"ctest" : "/nix/store/np45wjc61sy6d021dnrgyizga8f859k5-cmake-3.31.6/bin/ctest",
			"root" : "/nix/store/np45wjc61sy6d021dnrgyizga8f859k5-cmake-3.31.6/share/cmake-3.31"
		},
		"version" : 
		{
			"isDirty" : false,
			"major" : 3,
			"minor" : 31,
			"patch" : 6,
			"string" : "3.31.6",
			"suffix" : ""
		}
	},
	"objects" : 
	[
		{
			"jsonFile" : "codemodel-v2-9076028621c3d962bbb3.json",
			"kind" : "codemodel",
			"version" : 
			{
				"major" : 2,
				"minor" : 7
			}
		},
		{
			"jsonFile" : "configureLog-v1-f709ecce8b5f480a6247.json",
			"kind" : "configureLog",
			"version" : 
			{
				"major" : 1,
				"minor" : 0
			}
		},
		{
			"jsonFile" : "cache-v2-5cde9c62d22d836bac27.json",
			"kind" : "cache",
			"version" : 
			{
				"major" : 2,
				"minor" : 0
			}
		},
		{
			"jsonFile" : "cmakeFiles-v1-dbe5a12212ee2fd5c493.json",
			"kind" : "cmakeFiles",
			"version" : 
			{
				"major" : 1,
				"minor" : 1
			}
		},
		{
			"jsonFile" : "toolchains-v1-728bb6e01ca3d3e1f116.json",
			"kind" : "toolchains",
			"version" : 
			{
				"major" : 1,
				"minor" : 0
			}
		}
	],
	"reply" : 
	{
		"client-neocmake" : 
		{
			"query.json" : 
			{
				"requests" : 
				[
					{
						"kind" : "codemodel",
						"version" : 
						[
							{
								"major" : 2,
								"minor" : 7
							}
						]
					},
					{
						"kind" : "configureLog",
						"version" : 
						[
							{
								"major" : 1,
								"minor" : 0
							}
						]
					},
					{
						"kind" : "cache",
						"version" : 
						[
							{
								"major" : 2,
								"minor" : 0
							}
						]
					},
					{
						"kind" : "cmakeFiles",
						"version" : 
						[
							{
								"major" : 1,
								"minor" : 1
							}
						]
					},
					{
						"kind" : "toolchains",
						"version" : 
						[
							{
								"major" : 1,
								"minor" : 0
							}
						]
					}
				],
				"responses" : 
				[
					{
						"jsonFile" : "codemodel-v2-9076028621c3d962bbb3.json",
						"kind" : "codemodel",
						"version" : 
						{
							"major" : 2,
							"minor" : 7
						}
					},
					{
						"jsonFile" : "configureLog-v1-f709ecce8b5f480a6247.json",
						"kind" : "configureLog",
						"version" : 
						{
							"major" : 1,
							"minor" : 0
						}
					},
					{
						"jsonFile" : "cache-v2-5cde9c62d22d836bac27.json",
						"kind" : "cache",
						"version" : 
						{
							"major" : 2,
							"minor" : 0
						}
					},
					{
						"jsonFile" : "cmakeFiles-v1-dbe5a12212ee2fd5c493.json",
						"kind" : "cmakeFiles",
						"version" : 
						{
							"major" : 1,
							"minor" : 1
						}
					},
					{
						"jsonFile" : "toolchains-v1-728bb6e01ca3d3e1f116.json",
						"kind" : "toolchains",
						"version" : 
						{
							"major" : 1,
							"minor" : 0
						}
					}
				]
			}
		},
		"client-vscode" : 
		{
			"query.json" : 
			{
				"requests" : 
				[
					{
						"kind" : "cache",
						"version" : 2
					},
					{
						"kind" : "codemodel",
						"version" : 2
					},
					{
						"kind" : "toolchains",
						"version" : 1
					},
					{
						"kind" : "cmakeFiles",
						"version" : 1
					}
				],
				"responses" : 
				[
					{
						"jsonFile" : "cache-v2-5cde9c62d22d836bac27.json",
						"kind" : "cache",
						"version" : 
						{
							"major" : 2,
							"minor" : 0
						}
					},
					{
						"jsonFile" : "codemodel-v2-9076028621c3d962bbb3.json",
						"kind" : "codemodel",
						"version" : 
						{
							"major" : 2,
							"minor" : 7
						}
					},
					{
						"jsonFile" : "toolchains-v1-728bb6e01ca3d3e1f116.json",
						"kind" : "toolchains",
						"version" : 
						{
							"major" : 1,
							"minor" : 0
						}
					},
					{
						"jsonFile" : "cmakeFiles-v1-dbe5a12212ee2fd5c493.json",
						"kind" : "cmakeFiles",
						"version" : 
						{
							"major" : 1,
							"minor" : 1
						}
					}
				]
			}
		}
	}
}
